sqlfs.py
sqlfs-0.1.0.dist-info/LICENSE
sqlfs-0.1.0.dist-info/METADATA
sqlfs-0.1.0.dist-info/WHEEL
sqlfs-0.1.0.dist-info/entry_points.txt
sqlfs-0.1.0.dist-info/top_level.txt
sqlfs-0.1.0.dist-info/RECORD
