Metadata-Version: 2.1
Name: sqlfs
Version: 0.1.0
Summary: SQLite FUSE filesystem
Home-page: https://pypi.org/project/sqlfs/
Author: Alexey Moroz
Author-email: me@mystex.me
License: MIT
Platform: any
Classifier: Development Status :: 5 - Production/Stable
Classifier: Intended Audience :: Developers
Classifier: Programming Language :: Python :: 3
Classifier: License :: OSI Approved :: MIT License
Classifier: Operating System :: MacOS
Classifier: Operating System :: POSIX
Classifier: Operating System :: POSIX :: Linux
Classifier: Topic :: System :: Filesystems
Requires-Dist: fusepy (>=3.0.1)
Requires-Dist: tzlocal (>=1.5.1)
